playsoundsimple/__init__.py
playsoundsimple/data/default.sf2
playsoundsimple/exceptions.py
playsoundsimple/fluidsynth.py
playsoundsimple/sound.py
playsoundsimple/sound.pyi
playsoundsimple/streamers/__init__.py
playsoundsimple/streamers/base.py
playsoundsimple/streamers/sds.py
playsoundsimple/units.py
playsoundsimple_py-0.8.4.dist-info/LICENSE
playsoundsimple_py-0.8.4.dist-info/METADATA
playsoundsimple_py-0.8.4.dist-info/WHEEL
playsoundsimple_py-0.8.4.dist-info/RECORD
