Metadata-Version: 2.1
Name: playsoundsimple-py
Version: 0.8.4
Summary: A simple library for playing sound files.
License: MIT
Author: Romanin
Author-email: semina054@gmail.com
Requires-Python: >=3.7,<3.12
Classifier: License :: OSI Approved :: MIT License
Classifier: Programming Language :: Python :: 3
Classifier: Programming Language :: Python :: 3.7
Classifier: Programming Language :: Python :: 3.8
Classifier: Programming Language :: Python :: 3.9
Classifier: Programming Language :: Python :: 3.10
Classifier: Programming Language :: Python :: 3.11
Requires-Dist: mutagen (>=1.47)
Requires-Dist: numpy (>=1.20)
Requires-Dist: sounddevice (>=0.4.6)
Requires-Dist: soundfile (>=0.12)
